imtime/__init__.py
imtime-0.1.0.dist-info/LICENSE
imtime-0.1.0.dist-info/METADATA
imtime-0.1.0.dist-info/WHEEL
imtime-0.1.0.dist-info/top_level.txt
imtime-0.1.0.dist-info/RECORD
