Metadata-Version: 2.2
Name: imtime
Version: 0.1.0
Summary: 一个简单的时间格式化工具
Author: imaitian
Author-email: 2018500@qq.com
Classifier: Programming Language :: Python :: 3
Classifier: License :: OSI Approved :: MIT License
Classifier: Operating System :: OS Independent
Requires-Python: >=3.7
License-File: LICENSE
Dynamic: author
Dynamic: author-email
Dynamic: classifier
Dynamic: description
Dynamic: description-content-type
Dynamic: requires-python
Dynamic: summary
